envcrypto/__init__.py
envcrypto/crypto.py
envcrypto/exceptions.py
envcrypto/levels.py
envcrypto/state.py
envcrypto/management/__init__.py
envcrypto/management/commands/__init__.py
envcrypto/management/commands/env-add.py
envcrypto/management/commands/env-create.py
envcrypto/management/commands/env-delete.py
envcrypto/management/commands/env-encryption.py
envcrypto/management/commands/env-key.py
envcrypto/management/commands/env-rotate.py
envcrypto/management/commands/env-show.py
envcrypto/management/commands/env-transcode.py
envcrypto/migrations/__init__.py
envcrypto/tests/__init__.py
envcrypto/tests/test_crypto.py
envcrypto/tests/test_levels.py
envcrypto/tests/test_state.py
envcrypto/tests/tests.py
test/__init__.py
test/settings.py
test/urls.py
test/wsgi.py
django_envcrypto-0.8.7.dist-info/METADATA
django_envcrypto-0.8.7.dist-info/WHEEL
django_envcrypto-0.8.7.dist-info/top_level.txt
django_envcrypto-0.8.7.dist-info/RECORD
